README.md
setup.cfg
setup.py
pybrackets/__init__.py
pybrackets/pybrackets.py
pybrackets.egg-info/PKG-INFO
pybrackets.egg-info/SOURCES.txt
pybrackets.egg-info/dependency_links.txt
pybrackets.egg-info/top_level.txt