Metadata-Version: 1.1
Name: pybrackets
Version: 1.0.1
Summary: Remove brackets
Home-page: https://stackoverflow.com/a/14603508
Author: pradyunsg
Author-email: UNKNOWN
License: MIT
Keywords: remove of brackets
Platform: UNKNOWN
Classifier: Development Status :: 5 - Production/Stable
Classifier: Intended Audience :: Developers
Classifier: License :: OSI Approved :: MIT License
Classifier: Natural Language :: English
Classifier: Operating System :: OS Independent
Classifier: Topic :: Software Development :: Internationalization
Classifier: Topic :: Scientific/Engineering :: Physics
